{"moduleName":null,"summaries":[{"symbol":{"__symbol":0,"members":[]},"metadata":{"__symbolic":"class","extends":{"__symbolic":"resolved","symbol":{"__symbol":1,"members":[]},"line":87,"character":56,"fileName":"src/components/xr/sumerian-scene-component/sumerian-scene-loading.component.ionic.ts"},"members":{"__ctor__":[{"__symbolic":"constructor"}]}},"type":{"summaryKind":1,"type":{"reference":{"__symbol":0,"members":[]},"diDeps":[],"lifecycleHooks":[]},"isComponent":true,"selector":"sumerian-scene-loading-ionic","exportAs":null,"inputs":{"loadPercentage":"loadPercentage","sceneName":"sceneName","sceneError":"sceneError"},"outputs":{},"hostListeners":{},"hostProperties":{},"hostAttributes":{},"providers":[],"viewProviders":[],"queries":[],"guards":{},"viewQueries":[],"entryComponents":[],"changeDetection":1,"template":{"ngContentSelectors":[],"encapsulation":2},"componentViewType":{"__symbol":2,"members":[]},"rendererType":{"__symbol":3,"members":[]},"componentFactory":{"__symbol":4,"members":[]}}}],"symbols":[{"__symbol":0,"name":"SumerianSceneLoadingComponentIonic","filePath":"./sumerian-scene-loading.component.ionic"},{"__symbol":1,"name":"SumerianSceneLoadingComponentCore","filePath":"./sumerian-scene-loading.component.core"},{"__symbol":2,"name":"View_SumerianSceneLoadingComponentIonic_0","filePath":"./sumerian-scene-loading.component.ionic.ngfactory"},{"__symbol":3,"name":"RenderType_SumerianSceneLoadingComponentIonic","filePath":"./sumerian-scene-loading.component.ionic.ngfactory"},{"__symbol":4,"name":"SumerianSceneLoadingComponentIonicNgFactory","filePath":"./sumerian-scene-loading.component.ionic.ngfactory"}]}