{"moduleName":null,"summaries":[{"symbol":{"__symbol":0,"members":[]},"metadata":{"__symbolic":"class","members":{"selected":[{"__symbolic":"property","decorators":[{"__symbolic":"call","expression":{"__symbolic":"resolved","symbol":{"__symbol":1,"members":[]},"line":42,"character":2,"fileName":"src/components/storage/s3-album-component/s3-album.component.core.ts"}}]}],"__ctor__":[{"__symbolic":"constructor","parameters":[{"__symbolic":"resolved","symbol":{"__symbol":2,"members":[]},"line":45,"character":39,"fileName":"src/components/storage/s3-album-component/s3-album.component.core.ts"}]}],"ngOnInit":[{"__symbolic":"method"}],"onImageSelected":[{"__symbolic":"method"}],"data":[{"__symbolic":"property","decorators":[{"__symbolic":"call","expression":{"__symbolic":"resolved","symbol":{"__symbol":3,"members":[]},"line":62,"character":2,"fileName":"src/components/storage/s3-album-component/s3-album.component.core.ts"}}]}],"path":[{"__symbolic":"property","decorators":[{"__symbolic":"call","expression":{"__symbolic":"resolved","symbol":{"__symbol":3,"members":[]},"line":70,"character":2,"fileName":"src/components/storage/s3-album-component/s3-album.component.core.ts"}}]}],"options":[{"__symbolic":"property","decorators":[{"__symbolic":"call","expression":{"__symbolic":"resolved","symbol":{"__symbol":3,"members":[]},"line":74,"character":2,"fileName":"src/components/storage/s3-album-component/s3-album.component.core.ts"}}]}],"getList":[{"__symbolic":"method"}]}},"type":{"summaryKind":1,"type":{"reference":{"__symbol":0,"members":[]},"diDeps":[{"isAttribute":false,"isHost":false,"isSelf":false,"isSkipSelf":false,"isOptional":false,"token":{"identifier":{"reference":{"__symbol":2,"members":[]}}}}],"lifecycleHooks":[0]},"isComponent":true,"selector":"amplify-s3-album-core","exportAs":null,"inputs":{"data":"data","path":"path","options":"options"},"outputs":{"selected":"selected"},"hostListeners":{},"hostProperties":{},"hostAttributes":{},"providers":[],"viewProviders":[],"queries":[],"guards":{},"viewQueries":[],"entryComponents":[],"changeDetection":1,"template":{"ngContentSelectors":[],"encapsulation":2},"componentViewType":{"__symbol":4,"members":[]},"rendererType":{"__symbol":5,"members":[]},"componentFactory":{"__symbol":6,"members":[]}}}],"symbols":[{"__symbol":0,"name":"S3AlbumComponentCore","filePath":"./s3-album.component.core"},{"__symbol":1,"name":"Output","filePath":"@angular/core/core"},{"__symbol":2,"name":"AmplifyService","filePath":"../../../providers/amplify.service"},{"__symbol":3,"name":"Input","filePath":"@angular/core/core"},{"__symbol":4,"name":"View_S3AlbumComponentCore_0","filePath":"./s3-album.component.core.ngfactory"},{"__symbol":5,"name":"RenderType_S3AlbumComponentCore","filePath":"./s3-album.component.core.ngfactory"},{"__symbol":6,"name":"S3AlbumComponentCoreNgFactory","filePath":"./s3-album.component.core.ngfactory"}]}